README.md
setup.py
gapml/__init__.py
gapml/address.py
gapml/dataset.py
gapml/pdf_res.py
gapml/segment.py
gapml/splitter.py
gapml/syntax.py
gapml/vision.py
gapml/vocabulary.py
gapml.egg-info/PKG-INFO
gapml.egg-info/SOURCES.txt
gapml.egg-info/dependency_links.txt
gapml.egg-info/requires.txt
gapml.egg-info/top_level.txt
gapml/lg/__init__.py
gapml/lg/word2int_de.py
gapml/lg/word2int_en.py
gapml/lg/word2int_es.py
gapml/lg/word2int_fr.py
gapml/lg/word2int_it.py
gapml/utils/__init__.py
gapml/utils/img_tools.py