Metadata-Version: 1.1
Name: gapml
Version: 0.9.4
Summary: NLP and CV Data Engineering Framework
Home-page: https://github.com/andrewferlitsch/Gap
Author: Andrew Ferlitsch
Author-email: aferlitsch@gmail.com
License: Apache 2.0
Project-URL: Documentation, https://andrewferlitsch.github.io/Gap/
Project-URL: Source Code, https://github.com/andrewferlitsch/Gap
Platform: UNKNOWN
Classifier: Development Status :: 3 - Alpha
Classifier: Topic :: Text Processing
Classifier: License :: OSI Approved :: Apache Software License
Classifier: Operating System :: Microsoft :: Windows
Classifier: Operating System :: MacOS
Classifier: Operating System :: POSIX :: Linux
Classifier: Programming Language :: Python :: 3
Classifier: Programming Language :: Python :: 3.0
Classifier: Programming Language :: Python :: 3.1
Classifier: Programming Language :: Python :: 3.2
Classifier: Programming Language :: Python :: 3.3
Classifier: Programming Language :: Python :: 3.4
Classifier: Programming Language :: Python :: 3.5
Classifier: Programming Language :: Python :: 3.6
Classifier: Programming Language :: Python :: 3.7
